protodriver/__init__.py
protodriver/app.py
protodriver/leddriver.py
ProtoDriver-0.0.2.dist-info/LICENSE
ProtoDriver-0.0.2.dist-info/METADATA
ProtoDriver-0.0.2.dist-info/WHEEL
ProtoDriver-0.0.2.dist-info/top_level.txt
ProtoDriver-0.0.2.dist-info/RECORD
